paketoi/__init__.py
paketoi/__main__.py
paketoi/resources/cp-python3.10-arm64.json
paketoi/resources/cp-python3.10-x86_64.json
paketoi/resources/cp-python3.11-arm64.json
paketoi/resources/cp-python3.11-x86_64.json
paketoi/resources/cp-python3.12-arm64.json
paketoi/resources/cp-python3.12-x86_64.json
paketoi/resources/cp-python3.13-arm64.json
paketoi/resources/cp-python3.13-x86_64.json
paketoi/resources/cp-python3.9-arm64.json
paketoi/resources/cp-python3.9-x86_64.json
paketoi-0.1.3.dist-info/LICENSE
paketoi-0.1.3.dist-info/METADATA
paketoi-0.1.3.dist-info/WHEEL
paketoi-0.1.3.dist-info/entry_points.txt
paketoi-0.1.3.dist-info/RECORD
