Metadata-Version: 2.3
Name: paketoi
Version: 0.1.3
Summary: Build AWS Lambda deployment packages (zip files) for Python projects
License: MIT
Author: Miikka Koskinen
Author-email: miikka.koskinen@iki.fi
Requires-Python: >=3.10,<3.15
Classifier: License :: OSI Approved :: MIT License
Classifier: Operating System :: OS Independent
Classifier: Programming Language :: Python :: 3
Classifier: Programming Language :: Python :: 3.10
Classifier: Programming Language :: Python :: 3.11
Classifier: Programming Language :: Python :: 3.12
Classifier: Programming Language :: Python :: 3.13
Requires-Dist: click (>=8.1.7,<9.0.0)
Requires-Dist: pex (>=2.63.0,<3.0.0)
Requires-Dist: repro-zipfile (>=0.4.1,<0.5.0)
Project-URL: Homepage, https://codeberg.org/miikka/paketoi
Project-URL: Repository, https://codeberg.org/miikka/paketoi
